openstef_models/__init__.py
openstef_models/explainability/__init__.py
openstef_models/explainability/mixins.py
openstef_models/explainability/plotters/__init__.py
openstef_models/explainability/plotters/feature_importance_plotter.py
openstef_models/integrations/__init__.py
openstef_models/integrations/joblib/__init__.py
openstef_models/integrations/joblib/joblib_model_serializer.py
openstef_models/integrations/mlflow/__init__.py
openstef_models/integrations/mlflow/mlflow_storage.py
openstef_models/integrations/mlflow/mlflow_storage_callback.py
openstef_models/mixins/__init__.py
openstef_models/mixins/callbacks.py
openstef_models/mixins/model_serializer.py
openstef_models/models/__init__.py
openstef_models/models/component_splitting_model.py
openstef_models/models/forecasting_model.py
openstef_models/models/component_splitting/__init__.py
openstef_models/models/component_splitting/component_splitter.py
openstef_models/models/component_splitting/constant_component_splitter.py
openstef_models/models/component_splitting/linear_component_splitter.py
openstef_models/models/component_splitting/linear_component_splitter_model/linear_component_splitter_model.z
openstef_models/models/component_splitting/linear_component_splitter_model/linear_component_splitter_model.z.license
openstef_models/models/forecasting/__init__.py
openstef_models/models/forecasting/base_case_forecaster.py
openstef_models/models/forecasting/constant_median_forecaster.py
openstef_models/models/forecasting/flatliner_forecaster.py
openstef_models/models/forecasting/forecaster.py
openstef_models/models/forecasting/gblinear_forecaster.py
openstef_models/models/forecasting/xgboost_forecaster.py
openstef_models/presets/__init__.py
openstef_models/presets/forecasting_workflow.py
openstef_models/transforms/__init__.py
openstef_models/transforms/energy_domain/__init__.py
openstef_models/transforms/energy_domain/wind_power_feature_adder.py
openstef_models/transforms/general/__init__.py
openstef_models-4.0.0a10.dist-info/METADATA
openstef_models-4.0.0a10.dist-info/WHEEL
openstef_models-4.0.0a10.dist-info/RECORD
